prometheus_es_exporter/__init__.py
prometheus_es_exporter/__main__.py
prometheus_es_exporter/cluster_health_parser.py
prometheus_es_exporter/indices_aliases_parser.py
prometheus_es_exporter/indices_mappings_parser.py
prometheus_es_exporter/indices_stats_parser.py
prometheus_es_exporter/metrics.py
prometheus_es_exporter/nodes_stats_parser.py
prometheus_es_exporter/parser.py
prometheus_es_exporter/scheduler.py
prometheus_es_exporter/utils.py
prometheus_es_exporter-0.14.1.dist-info/LICENSE
prometheus_es_exporter-0.14.1.dist-info/METADATA
prometheus_es_exporter-0.14.1.dist-info/WHEEL
prometheus_es_exporter-0.14.1.dist-info/entry_points.txt
prometheus_es_exporter-0.14.1.dist-info/top_level.txt
prometheus_es_exporter-0.14.1.dist-info/RECORD
