Metadata-Version: 2.1
Name: prometheus-es-exporter
Version: 0.14.1
Summary: Elasticsearch query Prometheus exporter
Home-page: https://github.com/braedon/prometheus-es-exporter
Author: Braedon Vickers
Author-email: braedon.vickers@gmail.com
License: MIT
Keywords: monitoring prometheus exporter elasticsearch
Classifier: Development Status :: 4 - Beta
Classifier: Intended Audience :: Developers
Classifier: Intended Audience :: System Administrators
Classifier: Topic :: System :: Monitoring
Classifier: License :: OSI Approved :: MIT License
Classifier: Programming Language :: Python :: 3
Classifier: Programming Language :: Python :: 3.5
Classifier: Programming Language :: Python :: 3.6
Classifier: Programming Language :: Python :: 3.7
Classifier: Programming Language :: Python :: 3.8
Requires-Python: >=3.5
License-File: LICENSE
Requires-Dist: click
Requires-Dist: click-config-file
Requires-Dist: elasticsearch
Requires-Dist: jog
Requires-Dist: prometheus-client (>=0.6.0)
